__init__.py
life.py
lifebgp-0.1.0.dist-info/LICENSE
lifebgp-0.1.0.dist-info/METADATA
lifebgp-0.1.0.dist-info/WHEEL
lifebgp-0.1.0.dist-info/top_level.txt
lifebgp-0.1.0.dist-info/RECORD
