Metadata-Version: 2.1
Name: lifebgp
Version: 0.1.0
Summary: A Conway's Game of Life code. Part of Big Geodata Processing course
Author-email: Wenjie Cheng <w.cheng-1@student.utwente.nl>
License: MIT License
Project-URL: Repository, https://github.com/Wenjie-Cheng/Game-of-Life
Project-URL: Issues, https://github.com/Wenjie-Cheng/Game-of-Life/issues
Keywords: Conway's Game of Life
Classifier: Development Status :: 2 - Pre-Alpha
Classifier: Intended Audience :: Developers
Classifier: Intended Audience :: Science/Research
Classifier: Natural Language :: English
Classifier: Programming Language :: Python :: 3
Classifier: Programming Language :: Python :: 3.10
Classifier: Programming Language :: Python :: 3.11
Classifier: Programming Language :: Python :: 3.12
Requires-Python: >=3.8
License-File: LICENSE
Requires-Dist: line-profiler
Requires-Dist: memory-profiler
Requires-Dist: bitarray
Provides-Extra: dev
Requires-Dist: build; extra == "dev"
Requires-Dist: bump-my-version; extra == "dev"
Requires-Dist: ruff; extra == "dev"
Requires-Dist: tox; extra == "dev"
Requires-Dist: myst-parser; extra == "dev"
Provides-Extra: publishing
Requires-Dist: build; extra == "publishing"
Requires-Dist: twine; extra == "publishing"
Requires-Dist: wheel; extra == "publishing"
